afdcli/__init__.py
afdcli/client.py
afdcli/params.pickle
afdcli-0.3.2.data/scripts/afdcli
afdcli-0.3.2.dist-info/LICENSE
afdcli-0.3.2.dist-info/METADATA
afdcli-0.3.2.dist-info/WHEEL
afdcli-0.3.2.dist-info/top_level.txt
afdcli-0.3.2.dist-info/RECORD
