Metadata-Version: 2.1
Name: afdcli
Version: 0.3.2
Summary: Seismic waveform downloading client
Home-page: https://github.com/maratumba/afdcli
Author: Yaman Özakin
Author-email: 
License: MIT
Platform: UNKNOWN
Classifier: Programming Language :: Python :: 3
Classifier: License :: OSI Approved :: MIT License
Classifier: Operating System :: OS Independent
Classifier: Topic :: Scientific/Engineering :: Physics
Requires-Dist: requests
Requires-Dist: numpy
Requires-Dist: obspy
